dataset_image_annotator/__init__.py
dataset_image_annotator/__main__.py
dataset_image_annotator/conf.py
dataset_image_annotator/core.py
dataset_image_annotator/jobs.py
dataset_image_annotator/main_window.ui
dataset_image_annotator/upload.py
dataset_image_annotator/api/__init__.py
dataset_image_annotator/api/http.py
dataset_image_annotator/api/users.py
dataset_image_annotator/api/v1/__init__.py
dataset_image_annotator/api/v1/endpoints.py
dataset_image_annotator/api/v1/schemas.py
dataset_image_annotator/api_clients/__init__.py
dataset_image_annotator/api_clients/annotator.py
dataset_image_annotator/core/__init__.py
dataset_image_annotator/core/upload_handler.py
dataset_image_annotator/db/__init__.py
dataset_image_annotator/db/alembic.ini
dataset_image_annotator/db/helpers.py
dataset_image_annotator/db/models.py
dataset_image_annotator/db/user_db_helpers.py
dataset_image_annotator/db/migrations/__init__.py
dataset_image_annotator/db/migrations/env.py
dataset_image_annotator/db/migrations/script.py.mako
dataset_image_annotator/db/migrations/versions/20230115231801_339054a81cc6_initial.py
dataset_image_annotator-0.2.0.dist-info/AUTHORS.rst
dataset_image_annotator-0.2.0.dist-info/LICENSE
dataset_image_annotator-0.2.0.dist-info/METADATA
dataset_image_annotator-0.2.0.dist-info/WHEEL
dataset_image_annotator-0.2.0.dist-info/top_level.txt
dataset_image_annotator-0.2.0.dist-info/RECORD
