Metadata-Version: 2.2
Name: dataset-image-annotator
Version: 0.2.0
Summary: Image annotation tool
Home-page: https://github.com/kamikaze/dataset-image-annotator
Author: Oleg Korsak
Author-email: kamikaze.is.waiting.you@gmail.com
License: gpl-3
Project-URL: Documentation, https://github.com/kamikaze/dataset-image-annotator/wiki
Platform: any
Classifier: Development Status :: 4 - Beta
Classifier: Programming Language :: Python
Requires-Python: >=3.13
License-File: LICENSE
License-File: AUTHORS.rst
Requires-Dist: rawpy==0.24.0
Requires-Dist: Pillow==11.1.0
Requires-Dist: pydantic==2.10.6
Requires-Dist: tzdata==2025.1
Provides-Extra: desktop
Requires-Dist: PySide6-Essentials==6.8.1.1; extra == "desktop"
Provides-Extra: web
Requires-Dist: alembic==1.14.1; extra == "web"
Requires-Dist: asyncpg==0.30.0; extra == "web"
Requires-Dist: Authlib==1.4.1; extra == "web"
Requires-Dist: fastapi==0.115.7; extra == "web"
Requires-Dist: fastapi-pagination==0.12.34; extra == "web"
Requires-Dist: fastapi-users-db-sqlalchemy==7.0.0; extra == "web"
Requires-Dist: fastapi-users[sqlalchemy]==14.0.1; extra == "web"
Requires-Dist: numpy==2.2.2; extra == "web"
Requires-Dist: orjson==3.10.15; extra == "web"
Requires-Dist: passlib[argon2]==1.7.4; extra == "web"
Requires-Dist: PyJWT==2.10.1; extra == "web"
Requires-Dist: python-dateutil==2.9.0.post0; extra == "web"
Requires-Dist: opencv-python==4.11.0.86; extra == "web"
Requires-Dist: python3-commons==0.6.5; extra == "web"
Requires-Dist: SQLAlchemy==2.0.37; extra == "web"
Requires-Dist: uvicorn[standard]==0.34.0; extra == "web"
Requires-Dist: uvloop==0.21.0; extra == "web"
Provides-Extra: testing
Requires-Dist: pytest; extra == "testing"
Requires-Dist: pytest-cov; extra == "testing"
